{"type":"object","properties":{"content":{"type":"array","items":{"type":"object","properties":{"userCourseId":{"type":"integer","format":"int64"},"courseId":{"type":"integer","format":"int64"},"courseTitle":{"type":"string"},"courseDescription":{"type":"string"},"durationDays":{"type":"integer","format":"int32"},"assignedByDoctorName":{"type":"string"},"assignedAt":{"type":"string","format":"date-time"},"notes":{"type":"string"},"canStart":{"type":"boolean"},"hasStarted":{"type":"boolean"},"isCompleted":{"type":"boolean"}},"x-readme-ref-name":"MyAssignedCourseResponse"}},"page":{"type":"object","properties":{"size":{"type":"integer","format":"int64"},"number":{"type":"integer","format":"int64"},"totalElements":{"type":"integer","format":"int64"},"totalPages":{"type":"integer","format":"int64"}},"x-readme-ref-name":"PageMetadata"}},"x-readme-ref-name":"PagedModelMyAssignedCourseResponse"}