{
  "allOf": [
    { "$ref": "#/components/schemas/UpdateStaffRequest" },
    {
      "type": "object",
      "properties": {
        "specialization": {
          "type": "string",
          "description": "Doctor's medical specialization",
          "example": "Orthopedics"
        },
        "isPublic": {
          "type": "boolean",
          "description": "Whether this doctor is visible in the mobile app"
        },
        "profileImageUrl": {
          "type": "string",
          "description": "Object key or URL of the doctor's profile image"
        }
      }
    }
  ],
  "description": "Update request for Doctor staff",
  "required": ["email", "fullName", "staffType"],
  "x-readme-ref-name": "UpdateDoctorRequest"
}
